whuapi/__init__.py
whuapi/config.py
whuapi/api/__init__.py
whuapi/api/login.py
whuapi/api/student.py
whuapi-0.0.1.dist-info/LICENSE
whuapi-0.0.1.dist-info/METADATA
whuapi-0.0.1.dist-info/WHEEL
whuapi-0.0.1.dist-info/top_level.txt
whuapi-0.0.1.dist-info/RECORD
