Metadata-Version: 2.1
Name: whuapi
Version: 0.0.1
Summary: 新版武汉大学教务系统API
Home-page: https://github.com/yaoyue123/whuapi
Author: yaoyue123
Author-email: mcj1129@outlook.com
License: UNKNOWN
Platform: UNKNOWN
Classifier: Intended Audience :: Developers
Classifier: License :: OSI Approved :: MIT License
Classifier: Programming Language :: Python :: 3
Classifier: Programming Language :: Python :: 3.4
Classifier: Programming Language :: Python :: 3.5
Classifier: Programming Language :: Python :: 3.6
Requires-Python: >=3.0.0
Requires-Dist: requests
Requires-Dist: bs4
Requires-Dist: rsa
Requires-Dist: Crypto
